LICENSE
MANIFEST.in
README.rst
setup.py
django_counter_field_py3/__init__.py
django_counter_field_py3/counter.py
django_counter_field_py3/fields.py
django_counter_field_py3.egg-info/PKG-INFO
django_counter_field_py3.egg-info/SOURCES.txt
django_counter_field_py3.egg-info/dependency_links.txt
django_counter_field_py3.egg-info/not-zip-safe
django_counter_field_py3.egg-info/requires.txt
django_counter_field_py3.egg-info/top_level.txt
django_counter_field_py3/__pycache__/__init__.cpython-36.pyc
django_counter_field_py3/__pycache__/counter.cpython-36.pyc
django_counter_field_py3/__pycache__/fields.cpython-36.pyc
django_counter_field_py3/management/__init__.py
django_counter_field_py3/management/__pycache__/__init__.cpython-36.pyc
django_counter_field_py3/management/commands/__init__.py
django_counter_field_py3/management/commands/list_counters.py
django_counter_field_py3/management/commands/rebuild_counter.py
django_counter_field_py3/management/commands/__pycache__/__init__.cpython-36.pyc
django_counter_field_py3/management/commands/__pycache__/rebuild_counter.cpython-36.pyc
docs/Makefile
docs/__init__.py
docs/source/__init__.py
docs/source/conf.py
docs/source/django_model_changes.rst
docs/source/index.rst