Metadata-Version: 1.1
Name: django-counter-field-py3
Version: 0.0.1.2
Summary: python3 fork of django-counter-field
Home-page: https://github.com/danilke/django_counter_field_py3
Author: Danila Kulakov, Ian Price
Author-email: kdanilke@gmail.com, iprice@thermaline.com
License: MIT License
Platform: UNKNOWN
Classifier: Environment :: Web Environment
Classifier: Framework :: Django
Classifier: Intended Audience :: Developers
Classifier: License :: OSI Approved :: MIT License
Classifier: Operating System :: OS Independent
Classifier: Programming Language :: Python
Classifier: Programming Language :: Python :: 2
Classifier: Programming Language :: Python :: 2.7
Classifier: Programming Language :: Python :: 3
Classifier: Programming Language :: Python :: 3.6
Classifier: Topic :: Internet :: WWW/HTTP
Classifier: Topic :: Internet :: WWW/HTTP :: Dynamic Content
